oborpc/__init__.py
oborpc/decorator.py
oborpc/exception.py
oborpc/security.py
oborpc/base/__init__.py
oborpc/base/meta.py
oborpc/builder/__init__.py
oborpc/builder/_base.py
oborpc/builder/_client.py
oborpc/builder/_server.py
oborpc/builder/fastapi.py
oborpc/builder/flask.py
oborpc-0.3.1.dist-info/LICENSE
oborpc-0.3.1.dist-info/METADATA
oborpc-0.3.1.dist-info/WHEEL
oborpc-0.3.1.dist-info/top_level.txt
oborpc-0.3.1.dist-info/RECORD
