Metadata-Version: 2.2
Name: oborpc
Version: 0.3.1
Summary: An easy setup object oriented RPC. Built-in setup for FastAPI and Flask
Home-page: https://github.com/Danangjoyoo/oborpc
Author: danangjoyoo (Agus Danangjoyo)
Author-email: <agus.danangjoyo.blog@gmail.com>
Keywords: fastapi,flask,rpc,OOP
Classifier: Development Status :: 5 - Production/Stable
Classifier: Intended Audience :: Developers
Classifier: Programming Language :: Python :: 3.9
Classifier: Programming Language :: Python :: 3.10
Classifier: Programming Language :: Python :: 3.11
Classifier: Environment :: Web Environment
Classifier: Operating System :: OS Independent
Classifier: Typing :: Typed
License-File: LICENSE
Requires-Dist: httpx
Requires-Dist: pydantic
Requires-Dist: jsonref
Dynamic: author
Dynamic: author-email
Dynamic: classifier
Dynamic: description
Dynamic: description-content-type
Dynamic: home-page
Dynamic: keywords
Dynamic: requires-dist
Dynamic: summary
